gleaner/__init__.py
gleaner/cli.py
gleaner/helpers.py
gleaner/scraper.py
gleaner-0.1.3.dist-info/licenses/LICENSE
gleaner-0.1.3.dist-info/METADATA
gleaner-0.1.3.dist-info/WHEEL
gleaner-0.1.3.dist-info/entry_points.txt
gleaner-0.1.3.dist-info/top_level.txt
gleaner-0.1.3.dist-info/RECORD
