Metadata-Version: 2.4
Name: gleaner
Version: 0.1.3
Summary: Web scraper that finds all pages on a domain
License-Expression: MIT
License-File: LICENSE
Requires-Dist: requests
Requires-Dist: beautifulsoup4
Requires-Dist: tqdm
Dynamic: license-file
